hypervigilant/__init__.py
hypervigilant/_factory.py
hypervigilant/_handlers.py
hypervigilant/_otel.py
hypervigilant/core.py
hypervigilant/native.py
hypervigilant/py.typed
hypervigilant/structlog.py
hypervigilant-17.0.0.dist-info/METADATA
hypervigilant-17.0.0.dist-info/WHEEL
hypervigilant-17.0.0.dist-info/RECORD
