Metadata-Version: 2.4
Name: hypervigilant
Version: 17.0.0
Summary: A collection of code for hypervigilant - wrapper for instrumentation.
Project-URL: Homepage, https://github.com/gao-hongnan/hypervigilant
Project-URL: Documentation, https://github.com/gao-hongnan/hypervigilant/tree/main/playbook
Project-URL: Repository, https://github.com/gao-hongnan/hypervigilant
Project-URL: Issues, https://github.com/gao-hongnan/hypervigilant/issues
Project-URL: Changelog, https://github.com/gao-hongnan/hypervigilant/releases
Author-email: GAO Hongnan <hongnangao@gmail.com>
Maintainer-email: GAO Hongnan <hongnangao@gmail.com>
License: Apache-2.0
Classifier: Development Status :: 4 - Beta
Classifier: Intended Audience :: Developers
Classifier: License :: OSI Approved :: Apache Software License
Classifier: Operating System :: OS Independent
Classifier: Programming Language :: Python :: 3
Classifier: Programming Language :: Python :: 3.12
Classifier: Programming Language :: Python :: 3.13
Classifier: Topic :: Scientific/Engineering :: Artificial Intelligence
Classifier: Topic :: Software Development :: Libraries :: Python Modules
Classifier: Typing :: Typed
Requires-Python: >=3.12
Requires-Dist: pydantic-settings>=2.6.0
Requires-Dist: pydantic>=2.10.0
Requires-Dist: structlog>=24.0.0
Provides-Extra: otel
Requires-Dist: opentelemetry-api>=1.20.0; extra == 'otel'
Provides-Extra: playground
Requires-Dist: pydanticonf>=1.0.0; extra == 'playground'
Requires-Dist: rich>=13.9.4; extra == 'playground'
